asone/__init__.py
asone/__main__.py
asone/scraper.py
ucsdasone-0.1.0.dist-info/LICENSE
ucsdasone-0.1.0.dist-info/METADATA
ucsdasone-0.1.0.dist-info/WHEEL
ucsdasone-0.1.0.dist-info/top_level.txt
ucsdasone-0.1.0.dist-info/RECORD
